LICENSE
combinadics_fast.py
setup.py
combinadics_fast.egg-info/PKG-INFO
combinadics_fast.egg-info/SOURCES.txt
combinadics_fast.egg-info/dependency_links.txt
combinadics_fast.egg-info/requires.txt
combinadics_fast.egg-info/top_level.txt