Metadata-Version: 2.1
Name: combinadics-fast
Version: 1.0.1
Summary: Fast tool for converting unique numbers <-> unique k-combinations.
Home-page: https://github.com/andrew-healey/combinadics
Author: Andrew Healey
Author-email: doolie.healey@gmail.com
License-File: LICENSE
